caffe/__init__.py
caffe/proto/__init__.py
caffe/proto/caffe_pb2.py
caffe2/__init__.py
caffe2/contrib/__init__.py
caffe2/contrib/playground/AnyExp.py
caffe2/contrib/playground/AnyExpOnTerm.py
caffe2/contrib/playground/ModuleRegister.py
caffe2/contrib/playground/__init__.py
caffe2/contrib/playground/checkpoint.py
caffe2/contrib/playground/compute_loss.py
caffe2/contrib/playground/compute_topk_accuracy.py
caffe2/contrib/playground/meter.py
caffe2/contrib/playground/module_map.py
caffe2/contrib/playground/output_generator.py
caffe2/contrib/playground/resnetdemo/IN1k_resnet.py
caffe2/contrib/playground/resnetdemo/IN1k_resnet_no_test_model.py
caffe2/contrib/playground/resnetdemo/__init__.py
caffe2/contrib/playground/resnetdemo/caffe2_resnet50_default_forward.py
caffe2/contrib/playground/resnetdemo/caffe2_resnet50_default_param_update.py
caffe2/contrib/playground/resnetdemo/explicit_resnet_forward.py
caffe2/contrib/playground/resnetdemo/explicit_resnet_param_update.py
caffe2/contrib/playground/resnetdemo/gfs_IN1k.py
caffe2/contrib/playground/resnetdemo/override_no_test_model_no_checkpoint.py
caffe2/contrib/playground/resnetdemo/rendezvous_filestore.py
caffe2/contrib/tensorboard/__init__.py
caffe2/contrib/tensorboard/tensorboard.py
caffe2/contrib/tensorboard/tensorboard_exporter.py
caffe2/contrib/tensorboard/tensorboard_exporter_test.py
caffe2/contrib/tensorboard/tensorboard_test.py
caffe2/proto/__init__.py
caffe2/proto/caffe2_legacy_pb2.py
caffe2/proto/caffe2_pb2.py
caffe2/proto/hsm_pb2.py
caffe2/proto/metanet_pb2.py
caffe2/proto/predictor_consts_pb2.py
caffe2/proto/prof_dag_pb2.py
caffe2/python/__init__.py
caffe2/python/_import_c_extension.py
caffe2/python/allcompare_test.py
caffe2/python/attention.py
caffe2/python/benchmark_generator.py
caffe2/python/binarysize.py
caffe2/python/brew.py
caffe2/python/brew_test.py
caffe2/python/build.py
caffe2/python/cached_reader.py
caffe2/python/caffe2_pybind11_state.cpython-36m-darwin.so
caffe2-0.5.0a0.dev100.dist-info/METADATA
caffe2-0.5.0a0.dev100.dist-info/RECORD
caffe2-0.5.0a0.dev100.dist-info/WHEEL
caffe2-0.5.0a0.dev100.dist-info/top_level.txt
