Metadata-Version: 2.1
Name: caffe2
Version: 0.5.0a0.dev100
Summary: Tensors and Dynamic neural networks in Python with strong GPU acceleration
Home-page: UNKNOWN
Author: UNKNOWN
Author-email: UNKNOWN
License: UNKNOWN
Platform: UNKNOWN
Requires-Dist: protobuf
Requires-Dist: pyyaml
Requires-Dist: numpy
Requires-Dist: future
Requires-Dist: setuptools
Requires-Dist: six
